marta/__init__.py
marta/exceptions.py
marta/utils.py
marta/api/__init__.py
marta/api/bus_client.py
marta/api/client.py
marta/api/rail_client.py
marta/enums/__init__.py
marta/enums/bus_lines.py
marta/enums/direction.py
marta/enums/train_line.py
marta/enums/vehicle_type.py
marta/models/__init__.py
marta/models/arrival.py
marta/models/bus.py
marta/models/train.py
marta/models/train_station.py
marta/models/vehicle.py
marta_python-0.3.0.dist-info/METADATA
marta_python-0.3.0.dist-info/WHEEL
marta_python-0.3.0.dist-info/top_level.txt
marta_python-0.3.0.dist-info/RECORD
