Metadata-Version: 2.1
Name: marta-python
Version: 0.3.0
Summary: An API client for interacting with MARTA's live train and bus data.
Home-page: https://github.com/nwithan8/marta-python
Download-URL: https://github.com/nwithan8/marta-python/archive/refs/tags/0.3.0.tar.gz
Author: Nate Harris
Author-email: n8gr8gbln@gmail.com
License: GNU General Public License v3 (GPLv3)
Keywords: API,client,MARTA,transit,bus,train,Atlanta,Georgia,GTFS
Classifier: License :: OSI Approved :: GNU General Public License v3 (GPLv3)
Classifier: Development Status :: 4 - Beta
Classifier: Intended Audience :: Developers
Classifier: Topic :: Software Development :: Build Tools
Classifier: Programming Language :: Python :: 3
Classifier: Programming Language :: Python :: 3.7
Classifier: Programming Language :: Python :: 3.8
Classifier: Programming Language :: Python :: 3.9
Classifier: Programming Language :: Python :: 3.10
Classifier: Programming Language :: Python :: 3.11
Classifier: Topic :: Multimedia :: Video
Classifier: Topic :: Multimedia
Classifier: Topic :: Internet :: WWW/HTTP
Classifier: Operating System :: OS Independent
Requires-Python: >=3.7, <4
Requires-Dist: objectrest (==2.*)
Requires-Dist: gtfs-realtime-bindings (==0.0.7)
Requires-Dist: protobuf (==3.20.*)
Requires-Dist: packaging (==21.3.*)
Requires-Dist: typing-extensions
Provides-Extra: dev
Requires-Dist: black ; extra == 'dev'
Requires-Dist: flake8 ; extra == 'dev'
Requires-Dist: isort ; extra == 'dev'
Requires-Dist: pytest-cov (==3.*) ; extra == 'dev'
Requires-Dist: pytest-vcr (==1.*) ; extra == 'dev'
Requires-Dist: pytest (==7.*) ; extra == 'dev'
Requires-Dist: types-requests ; extra == 'dev'
Requires-Dist: types-urllib3 ; extra == 'dev'
Requires-Dist: vcrpy (==4.*) ; extra == 'dev'
